rss_parser/__init__.py
rss_parser/_parser.py
rss_parser/custom_decorators.py
rss_parser/models/__init__.py
rss_parser/models/atom/__init__.py
rss_parser/models/atom/atom.py
rss_parser/models/atom/entry.py
rss_parser/models/atom/feed.py
rss_parser/models/atom/person.py
rss_parser/models/atom/source.py
rss_parser/models/rss/__init__.py
rss_parser/models/rss/channel.py
rss_parser/models/rss/image.py
rss_parser/models/rss/item.py
rss_parser/models/rss/rss.py
rss_parser/models/rss/text_input.py
rss_parser/models/types/__init__.py
rss_parser/models/types/date.py
rss_parser/models/types/only_list.py
rss_parser/models/types/tag.py
rss_parser/models/utils.py
rss_parser/py.typed
rss_parser/pydantic_proxy.py
rss_parser-2.1.1.dist-info/LICENSE
rss_parser-2.1.1.dist-info/METADATA
rss_parser-2.1.1.dist-info/WHEEL
rss_parser-2.1.1.dist-info/RECORD
