Metadata-Version: 2.3
Name: rss-parser
Version: 2.1.1
Summary: Typed pythonic RSS/Atom parser
License: GPL-3.0
Keywords: python,python3,cli,rss,parser,gplv3,typed,typed-python
Author: dhvcc
Author-email: 1337kwiz@gmail.com
Requires-Python: >=3.9,<4.0
Classifier: Development Status :: 5 - Production/Stable
Classifier: Intended Audience :: Developers
Classifier: License :: OSI Approved :: GNU General Public License v3 (GPLv3)
Classifier: Natural Language :: English
Classifier: Operating System :: OS Independent
Classifier: Programming Language :: Python :: 3
Classifier: Programming Language :: Python :: 3.9
Classifier: Programming Language :: Python :: 3.10
Classifier: Programming Language :: Python :: 3.11
Classifier: Programming Language :: Python :: 3.12
Classifier: Programming Language :: Python :: 3.13
Classifier: Topic :: Software Development :: Libraries :: Python Modules
Classifier: Topic :: Text Processing :: Markup :: XML
Classifier: Typing :: Typed
Requires-Dist: pydantic (>1.9)
Requires-Dist: xmltodict (>=0.13.0,<0.14.0)
Project-URL: Bug Tracker, https://github.com/dhvcc/rss-parser/issues
Project-URL: Homepage, https://dhvcc.github.io/rss-parser
Project-URL: Source, https://github.com/dhvcc/rss-parser
